setup.py
ffmpegwrapper/__init__.py
ffmpegwrapper/codec.py
ffmpegwrapper/ffmpeg.py
ffmpegwrapper/filter.py
ffmpegwrapper/options.py
ffmpegwrapper.egg-info/PKG-INFO
ffmpegwrapper.egg-info/SOURCES.txt
ffmpegwrapper.egg-info/dependency_links.txt
ffmpegwrapper.egg-info/top_level.txt