Metadata-Version: 1.0
Name: ffmpegwrapper
Version: 0.1-dev
Summary: A simple wrapper for ffmpeg-cli
Home-page: http://github.com/interrupted/ffmpegwrapper
Author: Mathias Koehler
Author-email: mail@mathias.im
License: BSD
Keywords: Video Convert Ffmpeg
Platform: UNKNOWN
Classifier: Development Status :: 2 - Pre-Alpha
Classifier: Intended Audience :: Developers
Classifier: License :: OSI Approved :: BSD License
Classifier: Operating System :: OS Independent
Classifier: Programming Language :: Python
Classifier: Programming Language :: Python :: 2.7
Classifier: Programming Language :: Python :: 3
Classifier: Topic :: Multimedia :: Video
Classifier: Topic :: Software Development :: Libraries :: Python Modules
